{
  "repo": {
    "name": "better-auth/better-auth",
    "description": "The most comprehensive authentication framework for TypeScript",
    "stars": 26406,
    "forks": 2284,
    "openIssues": 649,
    "watchers": 37,
    "owner": "better-auth",
    "owner_avatar_url": "https://avatars.githubusercontent.com/u/163827765?v=4"
  },
  "contributors": [
    {
      "login": "Bekacru",
      "contributions": 3050,
      "avatar_url": "https://avatars.githubusercontent.com/u/86073083?v=4",
      "html_url": "https://github.com/Bekacru"
    },
    {
      "login": "himself65",
      "contributions": 625,
      "avatar_url": "https://avatars.githubusercontent.com/u/14026360?v=4",
      "html_url": "https://github.com/himself65"
    },
    {
      "login": "Kinfe123",
      "contributions": 312,
      "avatar_url": "https://avatars.githubusercontent.com/u/65047246?v=4",
      "html_url": "https://github.com/Kinfe123"
    },
    {
      "login": "ping-maxwell",
      "contributions": 295,
      "avatar_url": "https://avatars.githubusercontent.com/u/145994855?v=4",
      "html_url": "https://github.com/ping-maxwell"
    },
    {
      "login": "bytaesu",
      "contributions": 241,
      "avatar_url": "https://avatars.githubusercontent.com/u/166604494?v=4",
      "html_url": "https://github.com/bytaesu"
    },
    {
      "login": "jslno",
      "contributions": 82,
      "avatar_url": "https://avatars.githubusercontent.com/u/24737269?v=4",
      "html_url": "https://github.com/jslno"
    },
    {
      "login": "Paola3stefania",
      "contributions": 71,
      "avatar_url": "https://avatars.githubusercontent.com/u/84341268?v=4",
      "html_url": "https://github.com/Paola3stefania"
    },
    {
      "login": "jonathansamines",
      "contributions": 39,
      "avatar_url": "https://avatars.githubusercontent.com/u/1268268?v=4",
      "html_url": "https://github.com/jonathansamines"
    },
    {
      "login": "GautamBytes",
      "contributions": 35,
      "avatar_url": "https://avatars.githubusercontent.com/u/161146829?v=4",
      "html_url": "https://github.com/GautamBytes"
    },
    {
      "login": "frectonz",
      "contributions": 34,
      "avatar_url": "https://avatars.githubusercontent.com/u/53809656?v=4",
      "html_url": "https://github.com/frectonz"
    },
    {
      "login": "dvanmali",
      "contributions": 33,
      "avatar_url": "https://avatars.githubusercontent.com/u/15009722?v=4",
      "html_url": "https://github.com/dvanmali"
    },
    {
      "login": "renovate[bot]",
      "contributions": 30,
      "avatar_url": "https://avatars.githubusercontent.com/in/2740?v=4",
      "html_url": "https://github.com/apps/renovate"
    },
    {
      "login": "dependabot[bot]",
      "contributions": 27,
      "avatar_url": "https://avatars.githubusercontent.com/in/29110?v=4",
      "html_url": "https://github.com/apps/dependabot"
    },
    {
      "login": "BlankParticle",
      "contributions": 21,
      "avatar_url": "https://avatars.githubusercontent.com/u/130567419?v=4",
      "html_url": "https://github.com/BlankParticle"
    },
    {
      "login": "DePasqualeOrg",
      "contributions": 17,
      "avatar_url": "https://avatars.githubusercontent.com/u/25420077?v=4",
      "html_url": "https://github.com/DePasqualeOrg"
    },
    {
      "login": "hyoban",
      "contributions": 15,
      "avatar_url": "https://avatars.githubusercontent.com/u/38493346?v=4",
      "html_url": "https://github.com/hyoban"
    },
    {
      "login": "okisdev",
      "contributions": 15,
      "avatar_url": "https://avatars.githubusercontent.com/u/66008528?v=4",
      "html_url": "https://github.com/okisdev"
    },
    {
      "login": "reslear",
      "contributions": 14,
      "avatar_url": "https://avatars.githubusercontent.com/u/12596485?v=4",
      "html_url": "https://github.com/reslear"
    },
    {
      "login": "dagmawibabi",
      "contributions": 13,
      "avatar_url": "https://avatars.githubusercontent.com/u/44819176?v=4",
      "html_url": "https://github.com/dagmawibabi"
    },
    {
      "login": "luksch42",
      "contributions": 12,
      "avatar_url": "https://avatars.githubusercontent.com/u/46937006?v=4",
      "html_url": "https://github.com/luksch42"
    },
    {
      "login": "RobiMez",
      "contributions": 8,
      "avatar_url": "https://avatars.githubusercontent.com/u/53259730?v=4",
      "html_url": "https://github.com/RobiMez"
    },
    {
      "login": "erquhart",
      "contributions": 8,
      "avatar_url": "https://avatars.githubusercontent.com/u/2112202?v=4",
      "html_url": "https://github.com/erquhart"
    },
    {
      "login": "ShobhitPatra",
      "contributions": 8,
      "avatar_url": "https://avatars.githubusercontent.com/u/115853816?v=4",
      "html_url": "https://github.com/ShobhitPatra"
    },
    {
      "login": "LovelessCodes",
      "contributions": 7,
      "avatar_url": "https://avatars.githubusercontent.com/u/45143926?v=4",
      "html_url": "https://github.com/LovelessCodes"
    },
    {
      "login": "kzlar",
      "contributions": 7,
      "avatar_url": "https://avatars.githubusercontent.com/u/120426485?v=4",
      "html_url": "https://github.com/kzlar"
    },
    {
      "login": "t3duk",
      "contributions": 7,
      "avatar_url": "https://avatars.githubusercontent.com/u/79575096?v=4",
      "html_url": "https://github.com/t3duk"
    },
    {
      "login": "CrutchTheClutch",
      "contributions": 7,
      "avatar_url": "https://avatars.githubusercontent.com/u/22361526?v=4",
      "html_url": "https://github.com/CrutchTheClutch"
    },
    {
      "login": "GregorWedlich",
      "contributions": 6,
      "avatar_url": "https://avatars.githubusercontent.com/u/4109582?v=4",
      "html_url": "https://github.com/GregorWedlich"
    },
    {
      "login": "Netrifier",
      "contributions": 6,
      "avatar_url": "https://avatars.githubusercontent.com/u/92852012?v=4",
      "html_url": "https://github.com/Netrifier"
    },
    {
      "login": "hussein-raji-mappa",
      "contributions": 6,
      "avatar_url": "https://avatars.githubusercontent.com/u/110731000?v=4",
      "html_url": "https://github.com/hussein-raji-mappa"
    },
    {
      "login": "ShahriarKh",
      "contributions": 6,
      "avatar_url": "https://avatars.githubusercontent.com/u/31452340?v=4",
      "html_url": "https://github.com/ShahriarKh"
    },
    {
      "login": "tinkerer-shubh",
      "contributions": 6,
      "avatar_url": "https://avatars.githubusercontent.com/u/158483822?v=4",
      "html_url": "https://github.com/tinkerer-shubh"
    },
    {
      "login": "ahmed-abdat",
      "contributions": 5,
      "avatar_url": "https://avatars.githubusercontent.com/u/102254583?v=4",
      "html_url": "https://github.com/ahmed-abdat"
    },
    {
      "login": "oskar-gmerek",
      "contributions": 5,
      "avatar_url": "https://avatars.githubusercontent.com/u/53402105?v=4",
      "html_url": "https://github.com/oskar-gmerek"
    },
    {
      "login": "sajadmh",
      "contributions": 5,
      "avatar_url": "https://avatars.githubusercontent.com/u/75350476?v=4",
      "html_url": "https://github.com/sajadmh"
    },
    {
      "login": "typed-sigterm",
      "contributions": 5,
      "avatar_url": "https://avatars.githubusercontent.com/u/145281501?v=4",
      "html_url": "https://github.com/typed-sigterm"
    },
    {
      "login": "arlyon",
      "contributions": 5,
      "avatar_url": "https://avatars.githubusercontent.com/u/8715352?v=4",
      "html_url": "https://github.com/arlyon"
    },
    {
      "login": "Wufler",
      "contributions": 5,
      "avatar_url": "https://avatars.githubusercontent.com/u/87246869?v=4",
      "html_url": "https://github.com/Wufler"
    },
    {
      "login": "MuzzaiyyanHussain",
      "contributions": 5,
      "avatar_url": "https://avatars.githubusercontent.com/u/175098529?v=4",
      "html_url": "https://github.com/MuzzaiyyanHussain"
    },
    {
      "login": "jstri",
      "contributions": 5,
      "avatar_url": "https://avatars.githubusercontent.com/u/9337138?v=4",
      "html_url": "https://github.com/jstri"
    },
    {
      "login": "iqorex",
      "contributions": 5,
      "avatar_url": "https://avatars.githubusercontent.com/u/51821001?v=4",
      "html_url": "https://github.com/iqorex"
    },
    {
      "login": "grant0417",
      "contributions": 5,
      "avatar_url": "https://avatars.githubusercontent.com/u/7355421?v=4",
      "html_url": "https://github.com/grant0417"
    },
    {
      "login": "fuma-nama",
      "contributions": 5,
      "avatar_url": "https://avatars.githubusercontent.com/u/76240755?v=4",
      "html_url": "https://github.com/fuma-nama"
    },
    {
      "login": "ephraimduncan",
      "contributions": 5,
      "avatar_url": "https://avatars.githubusercontent.com/u/55143799?v=4",
      "html_url": "https://github.com/ephraimduncan"
    },
    {
      "login": "0xPratikPatil",
      "contributions": 4,
      "avatar_url": "https://avatars.githubusercontent.com/u/127599705?v=4",
      "html_url": "https://github.com/0xPratikPatil"
    },
    {
      "login": "rinarakaki",
      "contributions": 4,
      "avatar_url": "https://avatars.githubusercontent.com/u/13822753?v=4",
      "html_url": "https://github.com/rinarakaki"
    },
    {
      "login": "rbayliss",
      "contributions": 4,
      "avatar_url": "https://avatars.githubusercontent.com/u/654407?v=4",
      "html_url": "https://github.com/rbayliss"
    },
    {
      "login": "TheUntraceable",
      "contributions": 4,
      "avatar_url": "https://avatars.githubusercontent.com/u/73362400?v=4",
      "html_url": "https://github.com/TheUntraceable"
    },
    {
      "login": "AntonVishal",
      "contributions": 4,
      "avatar_url": "https://avatars.githubusercontent.com/u/166398166?v=4",
      "html_url": "https://github.com/AntonVishal"
    },
    {
      "login": "starslingdev[bot]",
      "contributions": 4,
      "avatar_url": "https://avatars.githubusercontent.com/in/2449837?v=4",
      "html_url": "https://github.com/apps/starslingdev"
    },
    {
      "login": "mezotv",
      "contributions": 4,
      "avatar_url": "https://avatars.githubusercontent.com/u/68947960?v=4",
      "html_url": "https://github.com/mezotv"
    },
    {
      "login": "max-programming",
      "contributions": 4,
      "avatar_url": "https://avatars.githubusercontent.com/u/51731966?v=4",
      "html_url": "https://github.com/max-programming"
    },
    {
      "login": "DevDuki",
      "contributions": 4,
      "avatar_url": "https://avatars.githubusercontent.com/u/72626889?v=4",
      "html_url": "https://github.com/DevDuki"
    },
    {
      "login": "kevcube",
      "contributions": 4,
      "avatar_url": "https://avatars.githubusercontent.com/u/716806?v=4",
      "html_url": "https://github.com/kevcube"
    },
    {
      "login": "paoloricciuti",
      "contributions": 4,
      "avatar_url": "https://avatars.githubusercontent.com/u/26281609?v=4",
      "html_url": "https://github.com/paoloricciuti"
    },
    {
      "login": "nevthereal",
      "contributions": 4,
      "avatar_url": "https://avatars.githubusercontent.com/u/81911421?v=4",
      "html_url": "https://github.com/nevthereal"
    },
    {
      "login": "matserix",
      "contributions": 4,
      "avatar_url": "https://avatars.githubusercontent.com/u/113344017?v=4",
      "html_url": "https://github.com/matserix"
    },
    {
      "login": "MBLVD",
      "contributions": 4,
      "avatar_url": "https://avatars.githubusercontent.com/u/149737198?v=4",
      "html_url": "https://github.com/MBLVD"
    },
    {
      "login": "nktnet1",
      "contributions": 4,
      "avatar_url": "https://avatars.githubusercontent.com/u/86177399?v=4",
      "html_url": "https://github.com/nktnet1"
    },
    {
      "login": "moshetanzer",
      "contributions": 4,
      "avatar_url": "https://avatars.githubusercontent.com/u/82201261?v=4",
      "html_url": "https://github.com/moshetanzer"
    },
    {
      "login": "canstand",
      "contributions": 4,
      "avatar_url": "https://avatars.githubusercontent.com/u/70889873?v=4",
      "html_url": "https://github.com/canstand"
    },
    {
      "login": "acusti",
      "contributions": 4,
      "avatar_url": "https://avatars.githubusercontent.com/u/517889?v=4",
      "html_url": "https://github.com/acusti"
    },
    {
      "login": "Konixy",
      "contributions": 4,
      "avatar_url": "https://avatars.githubusercontent.com/u/66780340?v=4",
      "html_url": "https://github.com/Konixy"
    },
    {
      "login": "aleclarson",
      "contributions": 4,
      "avatar_url": "https://avatars.githubusercontent.com/u/1925840?v=4",
      "html_url": "https://github.com/aleclarson"
    },
    {
      "login": "alisamadiii",
      "contributions": 4,
      "avatar_url": "https://avatars.githubusercontent.com/u/99729607?v=4",
      "html_url": "https://github.com/alisamadiii"
    },
    {
      "login": "QuintenStr",
      "contributions": 3,
      "avatar_url": "https://avatars.githubusercontent.com/u/91246551?v=4",
      "html_url": "https://github.com/QuintenStr"
    },
    {
      "login": "Pukimaa",
      "contributions": 3,
      "avatar_url": "https://avatars.githubusercontent.com/u/58347116?v=4",
      "html_url": "https://github.com/Pukimaa"
    },
    {
      "login": "paaauldev",
      "contributions": 3,
      "avatar_url": "https://avatars.githubusercontent.com/u/69087295?v=4",
      "html_url": "https://github.com/paaauldev"
    },
    {
      "login": "ngregrichardson",
      "contributions": 3,
      "avatar_url": "https://avatars.githubusercontent.com/u/25447795?v=4",
      "html_url": "https://github.com/ngregrichardson"
    },
    {
      "login": "NoHaxito",
      "contributions": 3,
      "avatar_url": "https://avatars.githubusercontent.com/u/83735848?v=4",
      "html_url": "https://github.com/NoHaxito"
    },
    {
      "login": "nelsonprsousa",
      "contributions": 3,
      "avatar_url": "https://avatars.githubusercontent.com/u/8364345?v=4",
      "html_url": "https://github.com/nelsonprsousa"
    },
    {
      "login": "aaronlin0122",
      "contributions": 3,
      "avatar_url": "https://avatars.githubusercontent.com/u/47508893?v=4",
      "html_url": "https://github.com/aaronlin0122"
    },
    {
      "login": "ahmed-m-abbass",
      "contributions": 3,
      "avatar_url": "https://avatars.githubusercontent.com/u/106502101?v=4",
      "html_url": "https://github.com/ahmed-m-abbass"
    },
    {
      "login": "Ridhim-RR",
      "contributions": 3,
      "avatar_url": "https://avatars.githubusercontent.com/u/98144669?v=4",
      "html_url": "https://github.com/Ridhim-RR"
    },
    {
      "login": "SaviruFr",
      "contributions": 3,
      "avatar_url": "https://avatars.githubusercontent.com/u/147316385?v=4",
      "html_url": "https://github.com/SaviruFr"
    },
    {
      "login": "yultyyev",
      "contributions": 3,
      "avatar_url": "https://avatars.githubusercontent.com/u/1553420?v=4",
      "html_url": "https://github.com/yultyyev"
    },
    {
      "login": "atinux",
      "contributions": 3,
      "avatar_url": "https://avatars.githubusercontent.com/u/904724?v=4",
      "html_url": "https://github.com/atinux"
    },
    {
      "login": "ThallesP",
      "contributions": 3,
      "avatar_url": "https://avatars.githubusercontent.com/u/76017384?v=4",
      "html_url": "https://github.com/ThallesP"
    },
    {
      "login": "ceolinwill",
      "contributions": 3,
      "avatar_url": "https://avatars.githubusercontent.com/u/4393133?v=4",
      "html_url": "https://github.com/ceolinwill"
    },
    {
      "login": "gwoodbridge",
      "contributions": 3,
      "avatar_url": "https://avatars.githubusercontent.com/u/5333942?v=4",
      "html_url": "https://github.com/gwoodbridge"
    },
    {
      "login": "limichange",
      "contributions": 3,
      "avatar_url": "https://avatars.githubusercontent.com/u/1947344?v=4",
      "html_url": "https://github.com/limichange"
    },
    {
      "login": "rovertrack",
      "contributions": 3,
      "avatar_url": "https://avatars.githubusercontent.com/u/160643895?v=4",
      "html_url": "https://github.com/rovertrack"
    },
    {
      "login": "marwanhilmi",
      "contributions": 3,
      "avatar_url": "https://avatars.githubusercontent.com/u/1442356?v=4",
      "html_url": "https://github.com/marwanhilmi"
    },
    {
      "login": "bortoz",
      "contributions": 3,
      "avatar_url": "https://avatars.githubusercontent.com/u/43854807?v=4",
      "html_url": "https://github.com/bortoz"
    },
    {
      "login": "alexander-cato",
      "contributions": 3,
      "avatar_url": "https://avatars.githubusercontent.com/u/52341592?v=4",
      "html_url": "https://github.com/alexander-cato"
    },
    {
      "login": "anmol-fzr",
      "contributions": 3,
      "avatar_url": "https://avatars.githubusercontent.com/u/88301047?v=4",
      "html_url": "https://github.com/anmol-fzr"
    },
    {
      "login": "braden-w",
      "contributions": 3,
      "avatar_url": "https://avatars.githubusercontent.com/u/13159333?v=4",
      "html_url": "https://github.com/braden-w"
    },
    {
      "login": "coopbri",
      "contributions": 3,
      "avatar_url": "https://avatars.githubusercontent.com/u/20056195?v=4",
      "html_url": "https://github.com/coopbri"
    },
    {
      "login": "D3visionNL",
      "contributions": 3,
      "avatar_url": "https://avatars.githubusercontent.com/u/35565878?v=4",
      "html_url": "https://github.com/D3visionNL"
    },
    {
      "login": "DIYgod",
      "contributions": 3,
      "avatar_url": "https://avatars.githubusercontent.com/u/8266075?v=4",
      "html_url": "https://github.com/DIYgod"
    },
    {
      "login": "Daniel-dev-s",
      "contributions": 3,
      "avatar_url": "https://avatars.githubusercontent.com/u/44831910?v=4",
      "html_url": "https://github.com/Daniel-dev-s"
    },
    {
      "login": "Kaseax",
      "contributions": 3,
      "avatar_url": "https://avatars.githubusercontent.com/u/80108547?v=4",
      "html_url": "https://github.com/Kaseax"
    },
    {
      "login": "mmikhan",
      "contributions": 3,
      "avatar_url": "https://avatars.githubusercontent.com/u/8946603?v=4",
      "html_url": "https://github.com/mmikhan"
    },
    {
      "login": "Siumauricio",
      "contributions": 3,
      "avatar_url": "https://avatars.githubusercontent.com/u/47042324?v=4",
      "html_url": "https://github.com/Siumauricio"
    },
    {
      "login": "marcellosso",
      "contributions": 3,
      "avatar_url": "https://avatars.githubusercontent.com/u/47645704?v=4",
      "html_url": "https://github.com/marcellosso"
    },
    {
      "login": "krishna-santosh",
      "contributions": 3,
      "avatar_url": "https://avatars.githubusercontent.com/u/75202541?v=4",
      "html_url": "https://github.com/krishna-santosh"
    },
    {
      "login": "juliusmarminge",
      "contributions": 3,
      "avatar_url": "https://avatars.githubusercontent.com/u/51714798?v=4",
      "html_url": "https://github.com/juliusmarminge"
    },
    {
      "login": "gregtjack",
      "contributions": 3,
      "avatar_url": "https://avatars.githubusercontent.com/u/40620725?v=4",
      "html_url": "https://github.com/gregtjack"
    },
    {
      "login": "wh5938316",
      "contributions": 3,
      "avatar_url": "https://avatars.githubusercontent.com/u/16160933?v=4",
      "html_url": "https://github.com/wh5938316"
    },
    {
      "login": "Hysterelius",
      "contributions": 3,
      "avatar_url": "https://avatars.githubusercontent.com/u/71912794?v=4",
      "html_url": "https://github.com/Hysterelius"
    }
  ],
  "stargazers": [
    {
      "login": "BarakXYZ",
      "starred_at": "2026-02-23T10:37:00Z",
      "avatar_url": "https://avatars.githubusercontent.com/u/94985214?v=4",
      "html_url": "https://github.com/BarakXYZ"
    },
    {
      "login": "binhkid2",
      "starred_at": "2026-02-23T09:57:28Z",
      "avatar_url": "https://avatars.githubusercontent.com/u/128137927?v=4",
      "company": "LacChinhSoft",
      "html_url": "https://github.com/binhkid2"
    },
    {
      "login": "mifmyth",
      "starred_at": "2026-02-23T08:51:36Z",
      "avatar_url": "https://avatars.githubusercontent.com/u/1690365?v=4",
      "html_url": "https://github.com/mifmyth"
    },
    {
      "login": "dasultras",
      "starred_at": "2026-02-23T08:35:23Z",
      "avatar_url": "https://avatars.githubusercontent.com/u/66926127?v=4",
      "html_url": "https://github.com/dasultras"
    },
    {
      "login": "omer9564",
      "starred_at": "2026-02-23T08:15:57Z",
      "avatar_url": "https://avatars.githubusercontent.com/u/42326891?v=4",
      "company": "@permitio ",
      "html_url": "https://github.com/omer9564"
    },
    {
      "login": "baohoangstan",
      "starred_at": "2026-02-23T07:14:25Z",
      "avatar_url": "https://avatars.githubusercontent.com/u/45784122?v=4",
      "company": "Freelancer",
      "html_url": "https://github.com/baohoangstan"
    },
    {
      "login": "leo1oel",
      "starred_at": "2026-02-23T07:06:15Z",
      "avatar_url": "https://avatars.githubusercontent.com/u/142374191?v=4",
      "company": "Tsinghua University",
      "html_url": "https://github.com/leo1oel"
    },
    {
      "login": "dkumza",
      "starred_at": "2026-02-23T06:47:27Z",
      "avatar_url": "https://avatars.githubusercontent.com/u/34168302?v=4",
      "html_url": "https://github.com/dkumza"
    },
    {
      "login": "tonymac129",
      "starred_at": "2026-02-23T04:29:44Z",
      "avatar_url": "https://avatars.githubusercontent.com/u/141281444?v=4",
      "company": "tj '29 @Mac-Web",
      "company_org": "hackclub",
      "company_public_members": 954,
      "html_url": "https://github.com/tonymac129"
    },
    {
      "login": "giiino",
      "starred_at": "2026-02-23T02:19:14Z",
      "avatar_url": "https://avatars.githubusercontent.com/u/52125591?v=4",
      "html_url": "https://github.com/giiino"
    },
    {
      "login": "psavarmattas",
      "starred_at": "2026-02-23T02:11:12Z",
      "avatar_url": "https://avatars.githubusercontent.com/u/68191388?v=4",
      "company": "Technological University of the Shannon",
      "company_org": "Technovt-Society",
      "company_public_members": 2,
      "html_url": "https://github.com/psavarmattas"
    },
    {
      "login": "miguelocana",
      "starred_at": "2026-02-23T00:21:56Z",
      "avatar_url": "https://avatars.githubusercontent.com/u/56848883?v=4",
      "html_url": "https://github.com/miguelocana"
    },
    {
      "login": "guerrerojuli",
      "starred_at": "2026-02-22T23:43:55Z",
      "avatar_url": "https://avatars.githubusercontent.com/u/120423480?v=4",
      "html_url": "https://github.com/guerrerojuli"
    },
    {
      "login": "albuquerquefabio",
      "starred_at": "2026-02-22T23:13:39Z",
      "avatar_url": "https://avatars.githubusercontent.com/u/6733883?v=4",
      "html_url": "https://github.com/albuquerquefabio"
    },
    {
      "login": "bmoyroud",
      "starred_at": "2026-02-22T22:36:31Z",
      "avatar_url": "https://avatars.githubusercontent.com/u/9058670?v=4",
      "company_org": "alchemyplatform",
      "company_public_members": 2,
      "html_url": "https://github.com/bmoyroud"
    },
    {
      "login": "roldan-eng-software",
      "starred_at": "2026-02-22T22:24:13Z",
      "avatar_url": "https://avatars.githubusercontent.com/u/239589803?v=4",
      "html_url": "https://github.com/roldan-eng-software"
    },
    {
      "login": "sanjeetiitr",
      "starred_at": "2026-02-22T21:10:29Z",
      "avatar_url": "https://avatars.githubusercontent.com/u/13379529?v=4",
      "html_url": "https://github.com/sanjeetiitr"
    },
    {
      "login": "ppriess",
      "starred_at": "2026-02-22T20:45:54Z",
      "avatar_url": "https://avatars.githubusercontent.com/u/48829787?v=4",
      "html_url": "https://github.com/ppriess"
    },
    {
      "login": "Kambi-V",
      "starred_at": "2026-02-22T20:39:52Z",
      "avatar_url": "https://avatars.githubusercontent.com/u/63726277?v=4",
      "html_url": "https://github.com/Kambi-V"
    },
    {
      "login": "din8sh",
      "starred_at": "2026-02-22T19:28:15Z",
      "avatar_url": "https://avatars.githubusercontent.com/u/130466943?v=4",
      "company": "UMBERI",
      "html_url": "https://github.com/din8sh"
    },
    {
      "login": "joy095",
      "starred_at": "2026-02-22T18:37:43Z",
      "avatar_url": "https://avatars.githubusercontent.com/u/96533682?v=4",
      "html_url": "https://github.com/joy095"
    },
    {
      "login": "Cardosofiles",
      "starred_at": "2026-02-22T18:19:30Z",
      "avatar_url": "https://avatars.githubusercontent.com/u/126399807?v=4",
      "company": "Unitri — Centro Universitário do Triândulo ",
      "html_url": "https://github.com/Cardosofiles"
    },
    {
      "login": "hamanovich",
      "starred_at": "2026-02-22T18:02:23Z",
      "avatar_url": "https://avatars.githubusercontent.com/u/4238784?v=4",
      "company": "EPAM Systems",
      "html_url": "https://github.com/hamanovich"
    },
    {
      "login": "parkle-suen",
      "starred_at": "2026-02-22T16:37:29Z",
      "avatar_url": "https://avatars.githubusercontent.com/u/25789351?v=4",
      "html_url": "https://github.com/parkle-suen"
    },
    {
      "login": "NetSkylz",
      "starred_at": "2026-02-22T14:01:16Z",
      "avatar_url": "https://avatars.githubusercontent.com/u/9570794?v=4",
      "html_url": "https://github.com/NetSkylz"
    },
    {
      "login": "timokoessler",
      "starred_at": "2026-02-22T13:31:57Z",
      "avatar_url": "https://avatars.githubusercontent.com/u/33259218?v=4",
      "company": "@AikidoSec",
      "company_org": "AikidoSec",
      "company_public_members": 19,
      "html_url": "https://github.com/timokoessler"
    },
    {
      "login": "ryannator",
      "starred_at": "2026-02-22T12:01:20Z",
      "avatar_url": "https://avatars.githubusercontent.com/u/126220362?v=4",
      "html_url": "https://github.com/ryannator"
    },
    {
      "login": "PiotrTrybala",
      "starred_at": "2026-02-22T10:50:46Z",
      "avatar_url": "https://avatars.githubusercontent.com/u/104249440?v=4",
      "html_url": "https://github.com/PiotrTrybala"
    },
    {
      "login": "mazzasaverio",
      "starred_at": "2026-02-22T10:49:27Z",
      "avatar_url": "https://avatars.githubusercontent.com/u/43672114?v=4",
      "html_url": "https://github.com/mazzasaverio"
    },
    {
      "login": "abhranil26",
      "starred_at": "2026-02-22T10:43:19Z",
      "avatar_url": "https://avatars.githubusercontent.com/u/30792751?v=4",
      "html_url": "https://github.com/abhranil26"
    },
    {
      "login": "kayznari",
      "starred_at": "2026-02-22T10:37:43Z",
      "avatar_url": "https://avatars.githubusercontent.com/u/106851925?v=4",
      "html_url": "https://github.com/kayznari"
    },
    {
      "login": "maxime-mroue",
      "starred_at": "2026-02-22T10:17:27Z",
      "avatar_url": "https://avatars.githubusercontent.com/u/263136677?v=4",
      "html_url": "https://github.com/maxime-mroue"
    },
    {
      "login": "Oluwatobi-Mustapha",
      "starred_at": "2026-02-22T08:53:04Z",
      "avatar_url": "https://avatars.githubusercontent.com/u/201377892?v=4",
      "html_url": "https://github.com/Oluwatobi-Mustapha"
    },
    {
      "login": "thotasyama",
      "starred_at": "2026-02-22T08:46:57Z",
      "avatar_url": "https://avatars.githubusercontent.com/u/106746176?v=4",
      "html_url": "https://github.com/thotasyama"
    },
    {
      "login": "lolney",
      "starred_at": "2026-02-22T08:43:10Z",
      "avatar_url": "https://avatars.githubusercontent.com/u/7378372?v=4",
      "html_url": "https://github.com/lolney"
    },
    {
      "login": "aalwayslucky",
      "starred_at": "2026-02-22T08:36:43Z",
      "avatar_url": "https://avatars.githubusercontent.com/u/73863117?v=4",
      "html_url": "https://github.com/aalwayslucky"
    },
    {
      "login": "bugkey24",
      "starred_at": "2026-02-22T05:31:26Z",
      "avatar_url": "https://avatars.githubusercontent.com/u/158387435?v=4",
      "html_url": "https://github.com/bugkey24"
    },
    {
      "login": "Timmy-Lane",
      "starred_at": "2026-02-22T04:12:52Z",
      "avatar_url": "https://avatars.githubusercontent.com/u/63181030?v=4",
      "html_url": "https://github.com/Timmy-Lane"
    },
    {
      "login": "woailuoisme",
      "starred_at": "2026-02-22T03:53:08Z",
      "avatar_url": "https://avatars.githubusercontent.com/u/4327462?v=4",
      "html_url": "https://github.com/woailuoisme"
    },
    {
      "login": "garygrossgarten",
      "starred_at": "2026-02-22T01:01:09Z",
      "avatar_url": "https://avatars.githubusercontent.com/u/8986373?v=4",
      "company_org": "fivethree-team",
      "company_public_members": 2,
      "html_url": "https://github.com/garygrossgarten"
    },
    {
      "login": "pellegrin-jerome",
      "starred_at": "2026-02-22T00:56:52Z",
      "avatar_url": "https://avatars.githubusercontent.com/u/5199547?v=4",
      "html_url": "https://github.com/pellegrin-jerome"
    },
    {
      "login": "ams187",
      "starred_at": "2026-02-22T00:09:13Z",
      "avatar_url": "https://avatars.githubusercontent.com/u/125750179?v=4",
      "html_url": "https://github.com/ams187"
    },
    {
      "login": "ddauer",
      "starred_at": "2026-02-21T22:32:17Z",
      "avatar_url": "https://avatars.githubusercontent.com/u/488153?v=4",
      "company_org": "wenergy",
      "company_public_members": 1,
      "html_url": "https://github.com/ddauer"
    },
    {
      "login": "miazga",
      "starred_at": "2026-02-21T21:48:06Z",
      "avatar_url": "https://avatars.githubusercontent.com/u/25554752?v=4",
      "company_org": "grupadotnet",
      "company_public_members": 12,
      "html_url": "https://github.com/miazga"
    },
    {
      "login": "alexander-densley",
      "starred_at": "2026-02-21T21:33:48Z",
      "avatar_url": "https://avatars.githubusercontent.com/u/89933800?v=4",
      "company": "@permitify-inc ",
      "html_url": "https://github.com/alexander-densley"
    },
    {
      "login": "danmesfin",
      "starred_at": "2026-02-21T21:32:32Z",
      "avatar_url": "https://avatars.githubusercontent.com/u/79213142?v=4",
      "company": "Arez Armada",
      "html_url": "https://github.com/danmesfin"
    },
    {
      "login": "amtagrwl",
      "starred_at": "2026-02-21T20:22:52Z",
      "avatar_url": "https://avatars.githubusercontent.com/u/5302320?v=4",
      "html_url": "https://github.com/amtagrwl"
    },
    {
      "login": "psg2",
      "starred_at": "2026-02-21T19:54:59Z",
      "avatar_url": "https://avatars.githubusercontent.com/u/14082115?v=4",
      "html_url": "https://github.com/psg2"
    },
    {
      "login": "yanjardim",
      "starred_at": "2026-02-21T18:13:54Z",
      "avatar_url": "https://avatars.githubusercontent.com/u/12006984?v=4",
      "html_url": "https://github.com/yanjardim"
    },
    {
      "login": "shoebHamim",
      "starred_at": "2026-02-21T17:01:09Z",
      "avatar_url": "https://avatars.githubusercontent.com/u/77540422?v=4",
      "html_url": "https://github.com/shoebHamim"
    }
  ],
  "stars_timeline": [
    {
      "date": "2024-07-02",
      "count": 1
    },
    {
      "date": "2024-09-23",
      "count": 1
    },
    {
      "date": "2024-09-27",
      "count": 9
    },
    {
      "date": "2024-09-28",
      "count": 89
    },
    {
      "date": "2026-01-01",
      "count": 24
    },
    {
      "date": "2026-01-02",
      "count": 29
    },
    {
      "date": "2026-01-03",
      "count": 32
    },
    {
      "date": "2026-01-04",
      "count": 42
    },
    {
      "date": "2026-01-05",
      "count": 37
    },
    {
      "date": "2026-01-06",
      "count": 46
    },
    {
      "date": "2026-01-07",
      "count": 43
    },
    {
      "date": "2026-01-08",
      "count": 45
    },
    {
      "date": "2026-01-09",
      "count": 54
    },
    {
      "date": "2026-01-10",
      "count": 27
    },
    {
      "date": "2026-01-11",
      "count": 22
    },
    {
      "date": "2026-01-12",
      "count": 63
    },
    {
      "date": "2026-01-13",
      "count": 41
    },
    {
      "date": "2026-01-14",
      "count": 46
    },
    {
      "date": "2026-01-15",
      "count": 43
    },
    {
      "date": "2026-01-16",
      "count": 30
    },
    {
      "date": "2026-01-17",
      "count": 41
    },
    {
      "date": "2026-01-18",
      "count": 52
    },
    {
      "date": "2026-01-19",
      "count": 59
    },
    {
      "date": "2026-01-20",
      "count": 46
    },
    {
      "date": "2026-01-21",
      "count": 42
    },
    {
      "date": "2026-01-22",
      "count": 28
    },
    {
      "date": "2026-01-23",
      "count": 47
    },
    {
      "date": "2026-01-24",
      "count": 29
    },
    {
      "date": "2026-01-25",
      "count": 43
    },
    {
      "date": "2026-01-26",
      "count": 39
    },
    {
      "date": "2026-01-27",
      "count": 46
    },
    {
      "date": "2026-01-28",
      "count": 42
    },
    {
      "date": "2026-01-29",
      "count": 38
    },
    {
      "date": "2026-01-30",
      "count": 28
    },
    {
      "date": "2026-01-31",
      "count": 25
    },
    {
      "date": "2026-02-01",
      "count": 16
    },
    {
      "date": "2026-02-02",
      "count": 37
    },
    {
      "date": "2026-02-03",
      "count": 27
    },
    {
      "date": "2026-02-04",
      "count": 31
    },
    {
      "date": "2026-02-05",
      "count": 41
    },
    {
      "date": "2026-02-06",
      "count": 34
    },
    {
      "date": "2026-02-07",
      "count": 27
    },
    {
      "date": "2026-02-08",
      "count": 27
    },
    {
      "date": "2026-02-09",
      "count": 34
    },
    {
      "date": "2026-02-10",
      "count": 34
    },
    {
      "date": "2026-02-11",
      "count": 36
    },
    {
      "date": "2026-02-12",
      "count": 29
    },
    {
      "date": "2026-02-13",
      "count": 36
    },
    {
      "date": "2026-02-14",
      "count": 19
    },
    {
      "date": "2026-02-15",
      "count": 28
    },
    {
      "date": "2026-02-16",
      "count": 25
    },
    {
      "date": "2026-02-17",
      "count": 31
    },
    {
      "date": "2026-02-18",
      "count": 29
    },
    {
      "date": "2026-02-19",
      "count": 31
    },
    {
      "date": "2026-02-20",
      "count": 41
    },
    {
      "date": "2026-02-21",
      "count": 22
    },
    {
      "date": "2026-02-22",
      "count": 30
    },
    {
      "date": "2026-02-23",
      "count": 12
    }
  ],
  "companies_summary": []
}
