[
  {
    "login": "yoonhoGo",
    "score": 22,
    "reason": "org @AUSG, large public member count",
    "avatar_url": "https://avatars.githubusercontent.com/u/6959851?v=4",
    "company": "@boostbrothers ",
    "company_org": "AUSG",
    "company_public_members": 95,
    "html_url": "https://github.com/yoonhoGo"
  },
  {
    "login": "stellaw1",
    "score": 22,
    "reason": "org @MLH-Fellowship, large public member count",
    "avatar_url": "https://avatars.githubusercontent.com/u/46392676?v=4",
    "company_org": "MLH-Fellowship",
    "company_public_members": 505,
    "html_url": "https://github.com/stellaw1"
  },
  {
    "login": "Benjampo",
    "score": 22,
    "reason": "org @lewagon, large public member count",
    "avatar_url": "https://avatars.githubusercontent.com/u/44669293?v=4",
    "company": "@Quanthome ",
    "company_org": "lewagon",
    "company_public_members": 124,
    "html_url": "https://github.com/Benjampo"
  },
  {
    "login": "yaambe",
    "score": 6,
    "reason": "org @Javaabu",
    "avatar_url": "https://avatars.githubusercontent.com/u/101970278?v=4",
    "company": "Javaabu",
    "company_org": "Javaabu",
    "company_public_members": 2,
    "html_url": "https://github.com/yaambe"
  },
  {
    "login": "dnya0",
    "score": 6,
    "reason": "org @LikeKNU",
    "avatar_url": "https://avatars.githubusercontent.com/u/84761609?v=4",
    "company_org": "LikeKNU",
    "company_public_members": 3,
    "html_url": "https://github.com/dnya0"
  },
  {
    "login": "joelop3",
    "score": 6,
    "reason": "org @sensesbit4",
    "avatar_url": "https://avatars.githubusercontent.com/u/8427448?v=4",
    "company": "Sensesbit",
    "company_org": "sensesbit4",
    "company_public_members": 1,
    "html_url": "https://github.com/joelop3"
  },
  {
    "login": "gieldakrypto",
    "score": 6,
    "reason": "org @ciota",
    "avatar_url": "https://avatars.githubusercontent.com/u/241211778?v=4",
    "company_org": "ciota",
    "company_public_members": 2,
    "html_url": "https://github.com/gieldakrypto"
  },
  {
    "login": "pavish",
    "score": 6,
    "reason": "org @mathesar-foundation",
    "avatar_url": "https://avatars.githubusercontent.com/u/11850603?v=4",
    "company": "Mathesar Foundation",
    "company_org": "mathesar-foundation",
    "company_public_members": 6,
    "html_url": "https://github.com/pavish"
  },
  {
    "login": "devaryakjha",
    "score": 6,
    "reason": "org @aryakumarjha",
    "avatar_url": "https://avatars.githubusercontent.com/u/99560530?v=4",
    "company": "@zerodhaonline ",
    "company_org": "aryakumarjha",
    "company_public_members": 1,
    "html_url": "https://github.com/devaryakjha"
  },
  {
    "login": "abdulvahidgok",
    "score": 6,
    "reason": "org @spro-dev",
    "avatar_url": "https://avatars.githubusercontent.com/u/30243729?v=4",
    "company_org": "spro-dev",
    "company_public_members": 1,
    "html_url": "https://github.com/abdulvahidgok"
  },
  {
    "login": "wmussack",
    "score": 0,
    "reason": "baseline",
    "avatar_url": "https://avatars.githubusercontent.com/u/4417255?v=4",
    "html_url": "https://github.com/wmussack"
  },
  {
    "login": "Naughty8020",
    "score": 0,
    "reason": "baseline",
    "avatar_url": "https://avatars.githubusercontent.com/u/169634290?v=4",
    "html_url": "https://github.com/Naughty8020"
  },
  {
    "login": "gooddaytoday",
    "score": 0,
    "reason": "baseline",
    "avatar_url": "https://avatars.githubusercontent.com/u/1484395?v=4",
    "company": "Loginom",
    "html_url": "https://github.com/gooddaytoday"
  },
  {
    "login": "yusifaliyevpro",
    "score": 0,
    "reason": "baseline",
    "avatar_url": "https://avatars.githubusercontent.com/u/114253515?v=4",
    "html_url": "https://github.com/yusifaliyevpro"
  },
  {
    "login": "binishjoshi",
    "score": 0,
    "reason": "baseline",
    "avatar_url": "https://avatars.githubusercontent.com/u/45104594?v=4",
    "html_url": "https://github.com/binishjoshi"
  },
  {
    "login": "a-keramat",
    "score": 0,
    "reason": "baseline",
    "avatar_url": "https://avatars.githubusercontent.com/u/30770127?v=4",
    "company": "Lockpost.ir",
    "html_url": "https://github.com/a-keramat"
  },
  {
    "login": "Hamzamelad",
    "score": 0,
    "reason": "baseline",
    "avatar_url": "https://avatars.githubusercontent.com/u/87945710?v=4",
    "html_url": "https://github.com/Hamzamelad"
  },
  {
    "login": "acterry",
    "score": 0,
    "reason": "baseline",
    "avatar_url": "https://avatars.githubusercontent.com/u/232669?v=4",
    "company": "MemberCentral.com",
    "html_url": "https://github.com/acterry"
  },
  {
    "login": "ronniemh",
    "score": 0,
    "reason": "baseline",
    "avatar_url": "https://avatars.githubusercontent.com/u/117962773?v=4",
    "company": "@carconnect-ec",
    "html_url": "https://github.com/ronniemh"
  },
  {
    "login": "bjmcqueen",
    "score": 0,
    "reason": "baseline",
    "avatar_url": "https://avatars.githubusercontent.com/u/29599965?v=4",
    "html_url": "https://github.com/bjmcqueen"
  },
  {
    "login": "daolanx",
    "score": 0,
    "reason": "baseline",
    "avatar_url": "https://avatars.githubusercontent.com/u/129248395?v=4",
    "html_url": "https://github.com/daolanx"
  },
  {
    "login": "2seoik",
    "score": 0,
    "reason": "baseline",
    "avatar_url": "https://avatars.githubusercontent.com/u/30066453?v=4",
    "html_url": "https://github.com/2seoik"
  },
  {
    "login": "zimo2013",
    "score": 0,
    "reason": "baseline",
    "avatar_url": "https://avatars.githubusercontent.com/u/8055636?v=4",
    "html_url": "https://github.com/zimo2013"
  },
  {
    "login": "TommyQTran",
    "score": 0,
    "reason": "baseline",
    "avatar_url": "https://avatars.githubusercontent.com/u/157635302?v=4",
    "html_url": "https://github.com/TommyQTran"
  },
  {
    "login": "ms31-dev",
    "score": 0,
    "reason": "baseline",
    "avatar_url": "https://avatars.githubusercontent.com/u/2014002?v=4",
    "html_url": "https://github.com/ms31-dev"
  },
  {
    "login": "yurseria",
    "score": 0,
    "reason": "baseline",
    "avatar_url": "https://avatars.githubusercontent.com/u/18681644?v=4",
    "company": "@boostbrothers",
    "html_url": "https://github.com/yurseria"
  },
  {
    "login": "yandw",
    "score": 0,
    "reason": "baseline",
    "avatar_url": "https://avatars.githubusercontent.com/u/6669169?v=4",
    "html_url": "https://github.com/yandw"
  },
  {
    "login": "RiteshChandnani",
    "score": 0,
    "reason": "baseline",
    "avatar_url": "https://avatars.githubusercontent.com/u/13303038?v=4",
    "html_url": "https://github.com/RiteshChandnani"
  },
  {
    "login": "MarcusElwin",
    "score": 0,
    "reason": "baseline",
    "avatar_url": "https://avatars.githubusercontent.com/u/8833114?v=4",
    "company": "@Kustom-Checkout",
    "html_url": "https://github.com/MarcusElwin"
  },
  {
    "login": "Chandrakanth10",
    "score": 0,
    "reason": "baseline",
    "avatar_url": "https://avatars.githubusercontent.com/u/82886677?v=4",
    "html_url": "https://github.com/Chandrakanth10"
  },
  {
    "login": "nathacks",
    "score": 0,
    "reason": "baseline",
    "avatar_url": "https://avatars.githubusercontent.com/u/62850359?v=4",
    "html_url": "https://github.com/nathacks"
  },
  {
    "login": "mrab54",
    "score": 0,
    "reason": "baseline",
    "avatar_url": "https://avatars.githubusercontent.com/u/4931489?v=4",
    "html_url": "https://github.com/mrab54"
  },
  {
    "login": "JonnerPaz",
    "score": 0,
    "reason": "baseline",
    "avatar_url": "https://avatars.githubusercontent.com/u/95718239?v=4",
    "html_url": "https://github.com/JonnerPaz"
  },
  {
    "login": "kollakek1",
    "score": 0,
    "reason": "baseline",
    "avatar_url": "https://avatars.githubusercontent.com/u/78259478?v=4",
    "html_url": "https://github.com/kollakek1"
  },
  {
    "login": "mbilesanmi",
    "score": 0,
    "reason": "baseline",
    "avatar_url": "https://avatars.githubusercontent.com/u/26195944?v=4",
    "company": "Carta",
    "html_url": "https://github.com/mbilesanmi"
  },
  {
    "login": "dimaaan21",
    "score": 0,
    "reason": "baseline",
    "avatar_url": "https://avatars.githubusercontent.com/u/36787146?v=4",
    "html_url": "https://github.com/dimaaan21"
  },
  {
    "login": "tensaeb",
    "score": 0,
    "reason": "baseline",
    "avatar_url": "https://avatars.githubusercontent.com/u/39292585?v=4",
    "html_url": "https://github.com/tensaeb"
  },
  {
    "login": "BarokDG",
    "score": 0,
    "reason": "baseline",
    "avatar_url": "https://avatars.githubusercontent.com/u/61631544?v=4",
    "html_url": "https://github.com/BarokDG"
  },
  {
    "login": "Tsuzat",
    "score": 0,
    "reason": "baseline",
    "avatar_url": "https://avatars.githubusercontent.com/u/70003855?v=4",
    "company": "Accenture",
    "html_url": "https://github.com/Tsuzat"
  },
  {
    "login": "A7149",
    "score": 0,
    "reason": "baseline",
    "avatar_url": "https://avatars.githubusercontent.com/u/241916504?v=4",
    "html_url": "https://github.com/A7149"
  },
  {
    "login": "yzqzy",
    "score": 0,
    "reason": "baseline",
    "avatar_url": "https://avatars.githubusercontent.com/u/96212026?v=4",
    "html_url": "https://github.com/yzqzy"
  },
  {
    "login": "metanet4jDev",
    "score": 0,
    "reason": "baseline",
    "avatar_url": "https://avatars.githubusercontent.com/u/8733990?v=4",
    "html_url": "https://github.com/metanet4jDev"
  },
  {
    "login": "AwaisOem",
    "score": 0,
    "reason": "baseline",
    "avatar_url": "https://avatars.githubusercontent.com/u/95477446?v=4",
    "html_url": "https://github.com/AwaisOem"
  },
  {
    "login": "huypm2",
    "score": 0,
    "reason": "baseline",
    "avatar_url": "https://avatars.githubusercontent.com/u/81728156?v=4",
    "html_url": "https://github.com/huypm2"
  },
  {
    "login": "crayonlu",
    "score": 0,
    "reason": "baseline",
    "avatar_url": "https://avatars.githubusercontent.com/u/180070272?v=4",
    "company": "HUST CSE & @BingyanStudio",
    "html_url": "https://github.com/crayonlu"
  },
  {
    "login": "TanSIRone",
    "score": 0,
    "reason": "baseline",
    "avatar_url": "https://avatars.githubusercontent.com/u/114329353?v=4",
    "html_url": "https://github.com/TanSIRone"
  },
  {
    "login": "PVUL",
    "score": 0,
    "reason": "baseline",
    "avatar_url": "https://avatars.githubusercontent.com/u/9632017?v=4",
    "html_url": "https://github.com/PVUL"
  },
  {
    "login": "yaksheng",
    "score": 0,
    "reason": "baseline",
    "avatar_url": "https://avatars.githubusercontent.com/u/17775630?v=4",
    "html_url": "https://github.com/yaksheng"
  },
  {
    "login": "phiponatchi",
    "score": 0,
    "reason": "baseline",
    "avatar_url": "https://avatars.githubusercontent.com/u/92184740?v=4",
    "company": "@sellmyrepo",
    "html_url": "https://github.com/phiponatchi"
  },
  {
    "login": "myfirnanda",
    "score": 0,
    "reason": "baseline",
    "avatar_url": "https://avatars.githubusercontent.com/u/82860149?v=4",
    "html_url": "https://github.com/myfirnanda"
  }
]